.coveragerc
.gitignore
.travis.yml
Dockerfile
LICENSE
README.md
__init__.py
contributors.txt
requirements-dev.txt
setup.cfg
setup.py
tox.ini
cbpro/.gitignore
cbpro/__init__.py
cbpro/authenticated_client.py
cbpro/cbpro_auth.py
cbpro/order_book.py
cbpro/public_client.py
cbpro/websocket_client.py
cbpro_next.egg-info/PKG-INFO
cbpro_next.egg-info/SOURCES.txt
cbpro_next.egg-info/dependency_links.txt
cbpro_next.egg-info/requires.txt
cbpro_next.egg-info/top_level.txt
tests/api_config.json.example
tests/test_authenticated_client.py
tests/test_public_client.py