Metadata-Version: 2.1
Name: cbpro-next
Version: 1.1.5
Summary: The unofficial Python client for the Coinbase Pro API
Home-page: https://github.com/itajaja/coinbasepro-python
Author: Daniel Paquin
Author-email: dpaq34@gmail.com
License: MIT
Download-URL: https://github.com/itajaja/coinbasepro-python/archive/master.zip
Keywords: gdax,gdax-api,orderbook,trade,bitcoin,ethereum,BTC,ETH,client,api,wrapper,exchange,crypto,currency,trading,trading-api,coinbase,pro,prime,coinbasepro
Platform: UNKNOWN
Classifier: Development Status :: 5 - Production/Stable
Classifier: Intended Audience :: Developers
Classifier: Intended Audience :: Financial and Insurance Industry
Classifier: Intended Audience :: Information Technology
Classifier: Topic :: Software Development :: Libraries :: Python Modules
Classifier: License :: OSI Approved :: MIT License
Classifier: Programming Language :: Python :: 2
Classifier: Programming Language :: Python :: 2.6
Classifier: Programming Language :: Python :: 2.7
Classifier: Programming Language :: Python :: 3
Classifier: Programming Language :: Python :: 3.3
Classifier: Programming Language :: Python :: 3.4
Classifier: Programming Language :: Python :: 3.5
Provides-Extra: test
